apimatic_calc_v_1/__init__.py
apimatic_calc_v_1/api_helper.py
apimatic_calc_v_1/apimatic_calc_v_1_client.py
apimatic_calc_v_1/configuration.py
apimatic_calc_v_1/decorators.py
apimatic_calc_v_1/controllers/__init__.py
apimatic_calc_v_1/controllers/base_controller.py
apimatic_calc_v_1/controllers/simple_calculator_controller.py
apimatic_calc_v_1/exceptions/__init__.py
apimatic_calc_v_1/exceptions/api_exception.py
apimatic_calc_v_1/http/__init__.py
apimatic_calc_v_1/http/http_call_back.py
apimatic_calc_v_1/http/http_client.py
apimatic_calc_v_1/http/http_context.py
apimatic_calc_v_1/http/http_method_enum.py
apimatic_calc_v_1/http/http_request.py
apimatic_calc_v_1/http/http_response.py
apimatic_calc_v_1/http/requests_client.py
apimatic_calc_v_1/models/__init__.py
apimatic_calc_v_1/models/operation_type_enum.py
tests/__init__.py
tests/http_response_catcher.py
tests/test_helper.py
tests/controllers/__init__.py
tests/controllers/controller_test_base.py
tests/controllers/test_simple_calculator_controller.py
apimatic_calc_v1-1.0.0.dist-info/LICENSE
apimatic_calc_v1-1.0.0.dist-info/METADATA
apimatic_calc_v1-1.0.0.dist-info/WHEEL
apimatic_calc_v1-1.0.0.dist-info/top_level.txt
apimatic_calc_v1-1.0.0.dist-info/RECORD
